{"data":[{"id":"e1my6bl44p3uj3uyfi285bnu","_name":"adfmaldkhbkl;","_team":"","_teacher":"","_email":"tigran.13.03.2004@gmail.com","_city":"","_school":"","_class":"","_descp":"","_urls":"asfdsfasdfsadfasdfads,havdjaksjdhas","likes":["lbo42bo0re4juckm"]},{"id":"9w8cznwpaj0izrj2sozu5opn","_name":"adfmaldkhbkl;","_team":"","_teacher":"","_email":"tigran.13.03.2004@gmail.com","_city":"","_school":"","_class":"","_descp":"","_urls":"asfdsfasdfsadfasdfads","likes":[]},{"id":"p29p5owgqy2mbkbs6yyvc7ec","_name":"Tigran","_team":"","_teacher":"","_email":"tigran.13.03.2004@gmail.com","_city":"","_school":"","_class":"","_descp":"","_urls":"asdahghscdhkalk;sjdvmasjkld","likes":[]},{"id":"p29p5owgqy2mbkbs6yyvc7ec","_name":"Tigran","_team":"","_teacher":"","_email":"tigran.13.03.2004@gmail.com","_city":"","_school":"","_class":"","_descp":"","_urls":"asdahghscdhkalk;sjdvmasjkld","likes":[]}]}
